catilo/__init__.py
catilo/catilo.py
catilo-0.2.6.dist-info/LICENSE
catilo-0.2.6.dist-info/METADATA
catilo-0.2.6.dist-info/WHEEL
catilo-0.2.6.dist-info/top_level.txt
catilo-0.2.6.dist-info/RECORD
