Metadata-Version: 2.1
Name: catilo
Version: 0.2.6
Summary: Manage configuration files from multiple source in python
Home-page: https://github.com/jptalukdar/catilo
Author: Jyotiplaban Talukdar
Author-email: work.jyotiplaban@gmail.com
License: UNKNOWN
Project-URL: Bug Tracker, https://github.com/jptalukdar/catilo/issues
Platform: UNKNOWN
Classifier: Programming Language :: Python :: 3
Classifier: License :: OSI Approved :: GNU General Public License v3 (GPLv3)
Classifier: Operating System :: OS Independent
Requires-Python: >=3.6
License-File: LICENSE
Requires-Dist: flatten-dict
Requires-Dist: pyyaml
Requires-Dist: jsonpath-ng
